ntt_json_model_parser/ModelProperty.py
ntt_json_model_parser/ObservableList.py
ntt_json_model_parser/Parser.py
ntt_json_model_parser/Signal.py
ntt_json_model_parser/__init__.py
ntt_json_model_parser/constants.py
tests/ListPropertyTesting.py
tests/ParserTesting.py
tests/SignalTesting.py
tests/__init__.py
ntt_json_model_parser-1.1.3.dist-info/LICENSE
ntt_json_model_parser-1.1.3.dist-info/METADATA
ntt_json_model_parser-1.1.3.dist-info/WHEEL
ntt_json_model_parser-1.1.3.dist-info/top_level.txt
ntt_json_model_parser-1.1.3.dist-info/RECORD
