Metadata-Version: 2.1
Name: ntt-json-model-parser
Version: 1.1.3
Summary: Convert data from .json file to python object
Home-page: https://github.com/threezinedine/ntt-json-model-parser
Author: threezinedine
Author-email: threezinedine@email.com
License: UNKNOWN
Project-URL: Source, https://github.com/threezinedine/ntt-json-model-parser
Project-URL: Tracker, https://github.com/threezinedine/ntt-json-model-parser/issues
Keywords: json,parser,object
Platform: UNKNOWN
Classifier: Development Status :: 3 - Alpha
Classifier: Intended Audience :: Developers
Classifier: License :: OSI Approved :: MIT License
Classifier: Programming Language :: Python :: 3
Classifier: Programming Language :: Python :: 3.6
Classifier: Programming Language :: Python :: 3.7
Classifier: Programming Language :: Python :: 3.8
Classifier: Programming Language :: Python :: 3.9
License-File: LICENSE
